winlnks.py
winlnks-0.2.2.dist-info/LICENSE
winlnks-0.2.2.dist-info/METADATA
winlnks-0.2.2.dist-info/WHEEL
winlnks-0.2.2.dist-info/entry_points.txt
winlnks-0.2.2.dist-info/top_level.txt
winlnks-0.2.2.dist-info/RECORD
