Metadata-Version: 2.1
Name: winlnks
Version: 0.2.2
Summary: Windows LNK File Parser and Creator
Author: BIG
License: MIT
Keywords: lnk,shortcut,windows
Classifier: Programming Language :: Python :: 3.6
Classifier: Programming Language :: Python :: 3.7
Classifier: Programming Language :: Python :: 3.8
Classifier: Programming Language :: Python :: 3.9
Classifier: Intended Audience :: Developers
Classifier: License :: OSI Approved :: MIT License
Classifier: Operating System :: OS Independent
Classifier: Topic :: Software Development :: Libraries :: Python Modules
License-File: LICENSE
Requires-Dist: colorama
Requires-Dist: asciitoart
